{
"meta":{"test_sets":["test"],"test_metrics":[{"best_value":"Min","name":"RMSE"}],"learn_metrics":[{"best_value":"Min","name":"RMSE"}],"launch_mode":"Train","parameters":"","iteration_count":500,"learn_sets":["learn"],"name":"experiment"},
"iterations":[
{"learn":[2.683129209],"iteration":0,"passed_time":3.889400524,"remaining_time":1940.810861,"test":[2.700546523]},
{"learn":[2.675163485],"iteration":1,"passed_time":7.656381251,"remaining_time":1906.438932,"test":[2.69308282]},
{"learn":[2.66735834],"iteration":2,"passed_time":11.59277263,"remaining_time":1920.535999,"test":[2.685626315]},
{"learn":[2.659810227],"iteration":3,"passed_time":15.67468199,"remaining_time":1943.660566,"test":[2.678690382]},
{"learn":[2.65276963],"iteration":4,"passed_time":19.39703039,"remaining_time":1920.306009,"test":[2.671799318]},
{"learn":[2.645913616],"iteration":5,"passed_time":23.1445755,"remaining_time":1905.570049,"test":[2.665527599]},
{"learn":[2.63928456],"iteration":6,"passed_time":27.03104249,"remaining_time":1903.757707,"test":[2.659385929]},
{"learn":[2.63286077],"iteration":7,"passed_time":30.85945114,"remaining_time":1897.856245,"test":[2.653316072]},
{"learn":[2.626683255],"iteration":8,"passed_time":39.15897891,"remaining_time":2136.339849,"test":[2.64762721]},
{"learn":[2.620659377],"iteration":9,"passed_time":43.32162371,"remaining_time":2122.759562,"test":[2.641983825]},
{"learn":[2.614797723],"iteration":10,"passed_time":47.43716626,"remaining_time":2108.797664,"test":[2.636561465]},
{"learn":[2.609130935],"iteration":11,"passed_time":51.57070326,"remaining_time":2097.208599,"test":[2.631349851]},
{"learn":[2.60334165],"iteration":12,"passed_time":56.57205095,"remaining_time":2119.276062,"test":[2.626006399]},
{"learn":[2.598021878],"iteration":13,"passed_time":61.27759216,"remaining_time":2127.207842,"test":[2.621195287]},
{"learn":[2.592577373],"iteration":14,"passed_time":66.39451533,"remaining_time":2146.755996,"test":[2.616200977]},
{"learn":[2.587396039],"iteration":15,"passed_time":72.64830962,"remaining_time":2197.611366,"test":[2.61133758]},
{"learn":[2.582655911],"iteration":16,"passed_time":82.02142603,"remaining_time":2330.373457,"test":[2.607020245]},
{"learn":[2.577696348],"iteration":17,"passed_time":86.93644666,"remaining_time":2327.964849,"test":[2.602545256]},
{"learn":[2.572792617],"iteration":18,"passed_time":91.77151778,"remaining_time":2323.268424,"test":[2.598118949]},
{"learn":[2.568208422],"iteration":19,"passed_time":95.94155592,"remaining_time":2302.597342,"test":[2.594177103]},
{"learn":[2.563685797],"iteration":20,"passed_time":99.95657006,"remaining_time":2279.961765,"test":[2.590201763]},
{"learn":[2.559331364],"iteration":21,"passed_time":104.0656068,"remaining_time":2261.061821,"test":[2.586357961]},
{"learn":[2.555069623],"iteration":22,"passed_time":108.3222289,"remaining_time":2246.508835,"test":[2.582460206]},
{"learn":[2.551010375],"iteration":23,"passed_time":112.4173926,"remaining_time":2229.611619,"test":[2.578777648]},
{"learn":[2.546782113],"iteration":24,"passed_time":116.6989537,"remaining_time":2217.280121,"test":[2.575079159]},
{"learn":[2.542782493],"iteration":25,"passed_time":121.5219818,"remaining_time":2215.439206,"test":[2.571575408]},
{"learn":[2.538939184],"iteration":26,"passed_time":126.3349325,"remaining_time":2213.200855,"test":[2.568123121]},
{"learn":[2.535121332],"iteration":27,"passed_time":131.3207884,"remaining_time":2213.69329,"test":[2.564710873]},
{"learn":[2.531382823],"iteration":28,"passed_time":136.2202484,"remaining_time":2212.404724,"test":[2.56146998]},
{"learn":[2.527682685],"iteration":29,"passed_time":141.3707715,"remaining_time":2214.808754,"test":[2.558273009]},
{"learn":[2.524058704],"iteration":30,"passed_time":146.4197473,"remaining_time":2215.189081,"test":[2.555212873]},
{"learn":[2.52035048],"iteration":31,"passed_time":151.4339334,"remaining_time":2214.721275,"test":[2.552022338]},
{"learn":[2.516855651],"iteration":32,"passed_time":156.5128188,"remaining_time":2214.893527,"test":[2.54902019]},
{"learn":[2.51362358],"iteration":33,"passed_time":161.5892555,"remaining_time":2214.723325,"test":[2.54638101]},
{"learn":[2.510399264],"iteration":34,"passed_time":166.498318,"remaining_time":2212.049082,"test":[2.543444564]},
{"learn":[2.507314787],"iteration":35,"passed_time":171.4088677,"remaining_time":2209.26985,"test":[2.540987927]},
{"learn":[2.50421991],"iteration":36,"passed_time":176.631048,"remaining_time":2210.275006,"test":[2.538380909]},
{"learn":[2.50103143],"iteration":37,"passed_time":181.4921488,"remaining_time":2206.562441,"test":[2.535699252]},
{"learn":[2.498016527],"iteration":38,"passed_time":186.3974869,"remaining_time":2203.313883,"test":[2.533165412]},
{"learn":[2.495133748],"iteration":39,"passed_time":191.4580951,"remaining_time":2201.768094,"test":[2.530749374]},
{"learn":[2.49236056],"iteration":40,"passed_time":196.3327405,"remaining_time":2197.968973,"test":[2.528428506]},
{"learn":[2.489272626],"iteration":41,"passed_time":201.4085578,"remaining_time":2196.312369,"test":[2.525936195]},
{"learn":[2.486324848],"iteration":42,"passed_time":206.2941251,"remaining_time":2192.474771,"test":[2.523426733]},
{"learn":[2.483602947],"iteration":43,"passed_time":211.169482,"remaining_time":2188.483723,"test":[2.521194334]},
{"learn":[2.480892658],"iteration":44,"passed_time":216.024617,"remaining_time":2184.248905,"test":[2.519131925]},
{"learn":[2.47830454],"iteration":45,"passed_time":220.9129123,"remaining_time":2180.314395,"test":[2.516971869]},
{"learn":[2.475805913],"iteration":46,"passed_time":225.9313357,"remaining_time":2177.593512,"test":[2.514997038]},
{"learn":[2.473266003],"iteration":47,"passed_time":230.8659058,"remaining_time":2173.98728,"test":[2.51296208]},
{"learn":[2.4706766],"iteration":48,"passed_time":235.927833,"remaining_time":2171.499035,"test":[2.510891773]},
{"learn":[2.467992689],"iteration":49,"passed_time":240.8578905,"remaining_time":2167.721015,"test":[2.508761202]},
{"learn":[2.465476181],"iteration":50,"passed_time":245.9622193,"remaining_time":2165.432088,"test":[2.506688638]},
{"learn":[2.463040868],"iteration":51,"passed_time":250.9291832,"remaining_time":2161.851424,"test":[2.504729128]},
{"learn":[2.460699846],"iteration":52,"passed_time":256.3127576,"remaining_time":2161.732125,"test":[2.502824822]},
{"learn":[2.458107161],"iteration":53,"passed_time":261.2908357,"remaining_time":2158.068754,"test":[2.500831833]},
{"learn":[2.455755064],"iteration":54,"passed_time":266.3995761,"remaining_time":2155.414752,"test":[2.499135982]},
{"learn":[2.453281327],"iteration":55,"passed_time":271.084623,"remaining_time":2149.313797,"test":[2.497048591]},
{"learn":[2.450721631],"iteration":56,"passed_time":275.8340914,"remaining_time":2143.763201,"test":[2.494815767]},
{"learn":[2.448627878],"iteration":57,"passed_time":280.7008139,"remaining_time":2139.133789,"test":[2.493495467]},
{"learn":[2.446321073],"iteration":58,"passed_time":285.9136203,"remaining_time":2137.083162,"test":[2.491663308]},
{"learn":[2.444021577],"iteration":59,"passed_time":290.9447423,"remaining_time":2133.594777,"test":[2.489871123]},
{"learn":[2.441633552],"iteration":60,"passed_time":295.9861684,"remaining_time":2130.129966,"test":[2.487990173]},
{"learn":[2.439456332],"iteration":61,"passed_time":301.1063801,"remaining_time":2127.170879,"test":[2.48649321]},
{"learn":[2.437248991],"iteration":62,"passed_time":306.0146069,"remaining_time":2122.67275,"test":[2.484772841]},
{"learn":[2.435128155],"iteration":63,"passed_time":311.1605984,"remaining_time":2119.781577,"test":[2.483347484]},
{"learn":[2.432947515],"iteration":64,"passed_time":316.2169486,"remaining_time":2116.221118,"test":[2.481707491]},
{"learn":[2.430903323],"iteration":65,"passed_time":321.2895725,"remaining_time":2112.722341,"test":[2.480139357]},
{"learn":[2.428947549],"iteration":66,"passed_time":326.1980851,"remaining_time":2108.115983,"test":[2.478552601]},
{"learn":[2.42692788],"iteration":67,"passed_time":331.1271879,"remaining_time":2103.631547,"test":[2.477087891]},
{"learn":[2.425039717],"iteration":68,"passed_time":336.1202943,"remaining_time":2099.534012,"test":[2.475683151]},
{"learn":[2.422950633],"iteration":69,"passed_time":341.3718437,"remaining_time":2096.998469,"test":[2.474122387]},
{"learn":[2.421186149],"iteration":70,"passed_time":346.4581872,"remaining_time":2093.388202,"test":[2.472706982]},
{"learn":[2.419266456],"iteration":71,"passed_time":351.7085666,"remaining_time":2090.712035,"test":[2.47128541]},
{"learn":[2.417265368],"iteration":72,"passed_time":356.7658209,"remaining_time":2086.835692,"test":[2.469742895]},
{"learn":[2.415381485],"iteration":73,"passed_time":361.9063756,"remaining_time":2083.406973,"test":[2.468504042]},
{"learn":[2.413515003],"iteration":74,"passed_time":366.8967956,"remaining_time":2079.081842,"test":[2.467063169]},
{"learn":[2.411722679],"iteration":75,"passed_time":372.1005753,"remaining_time":2075.929525,"test":[2.465736223]},
{"learn":[2.410024461],"iteration":76,"passed_time":377.2201534,"remaining_time":2072.261362,"test":[2.464629732]},
{"learn":[2.408215964],"iteration":77,"passed_time":382.2986078,"remaining_time":2068.333494,"test":[2.463634414]},
{"learn":[2.406470651],"iteration":78,"passed_time":387.4305983,"remaining_time":2064.661796,"test":[2.462422781]},
{"learn":[2.404402654],"iteration":79,"passed_time":392.5811887,"remaining_time":2061.051241,"test":[2.460778503]},
{"learn":[2.402722953],"iteration":80,"passed_time":397.7206724,"remaining_time":2057.345207,"test":[2.459467228]},
{"learn":[2.400951111],"iteration":81,"passed_time":402.9149296,"remaining_time":2053.883422,"test":[2.458240902]},
{"learn":[2.399270926],"iteration":82,"passed_time":408.0731445,"remaining_time":2050.19881,"test":[2.457076087]},
{"learn":[2.39742833],"iteration":83,"passed_time":413.2106765,"remaining_time":2046.376684,"test":[2.455718186]},
{"learn":[2.395814002],"iteration":84,"passed_time":418.2885432,"remaining_time":2042.232299,"test":[2.454707293]},
{"learn":[2.394187037],"iteration":85,"passed_time":423.3569822,"remaining_time":2038.020821,"test":[2.453686848]},
{"learn":[2.39247903],"iteration":86,"passed_time":428.3406347,"remaining_time":2033.387151,"test":[2.452462016]},
{"learn":[2.390898591],"iteration":87,"passed_time":433.2640766,"remaining_time":2028.463631,"test":[2.451604474]},
{"learn":[2.38908388],"iteration":88,"passed_time":438.3391577,"remaining_time":2024.24038,"test":[2.450268393]},
{"learn":[2.387700005],"iteration":89,"passed_time":443.2622932,"remaining_time":2019.306002,"test":[2.449321274]},
{"learn":[2.386134042],"iteration":90,"passed_time":448.0440612,"remaining_time":2013.736495,"test":[2.44807829]},
{"learn":[2.384579769],"iteration":91,"passed_time":453.0282989,"remaining_time":2009.082021,"test":[2.447152895]},
{"learn":[2.383320156],"iteration":92,"passed_time":457.8992778,"remaining_time":2003.924796,"test":[2.446247652]},
{"learn":[2.381820273],"iteration":93,"passed_time":462.5066693,"remaining_time":1997.635189,"test":[2.445263409]},
{"learn":[2.380107179],"iteration":94,"passed_time":467.306063,"remaining_time":1992.199532,"test":[2.444057372]},
{"learn":[2.378663735],"iteration":95,"passed_time":472.0055521,"remaining_time":1986.356698,"test":[2.442858059]},
{"learn":[2.37729291],"iteration":96,"passed_time":477.1507633,"remaining_time":1982.389254,"test":[2.442010604]},
{"learn":[2.375782314],"iteration":97,"passed_time":482.2475299,"remaining_time":1978.199051,"test":[2.441214603]},
{"learn":[2.374296057],"iteration":98,"passed_time":487.3284689,"remaining_time":1973.926425,"test":[2.440332368]},
{"learn":[2.372803088],"iteration":99,"passed_time":492.400452,"remaining_time":1969.601808,"test":[2.439480765]},
{"learn":[2.371309771],"iteration":100,"passed_time":497.088352,"remaining_time":1963.745074,"test":[2.438308475]},
{"learn":[2.369812858],"iteration":101,"passed_time":502.2400646,"remaining_time":1959.721036,"test":[2.437246833]},
{"learn":[2.368781884],"iteration":102,"passed_time":507.0262797,"remaining_time":1954.26634,"test":[2.436498915]},
{"learn":[2.367412665],"iteration":103,"passed_time":511.9502706,"remaining_time":1949.349107,"test":[2.435616368]},
{"learn":[2.366018445],"iteration":104,"passed_time":516.8152952,"remaining_time":1944.20992,"test":[2.434663869]},
{"learn":[2.364793156],"iteration":105,"passed_time":521.9278955,"remaining_time":1939.99614,"test":[2.4339779]},
{"learn":[2.363385036],"iteration":106,"passed_time":526.7772388,"remaining_time":1934.798643,"test":[2.433081308]},
{"learn":[2.361998163],"iteration":107,"passed_time":531.5075442,"remaining_time":1929.175531,"test":[2.432017853]},
{"learn":[2.36059968],"iteration":108,"passed_time":536.6635662,"remaining_time":1925.095912,"test":[2.43123112]},
{"learn":[2.359334491],"iteration":109,"passed_time":541.6715398,"remaining_time":1920.471823,"test":[2.430478551]},
{"learn":[2.35763766],"iteration":110,"passed_time":546.5205825,"remaining_time":1915.283843,"test":[2.429171787]},
{"learn":[2.356209882],"iteration":111,"passed_time":551.4665884,"remaining_time":1910.437824,"test":[2.428070285]},
{"learn":[2.354873341],"iteration":112,"passed_time":556.4833881,"remaining_time":1905.832488,"test":[2.427362035]},
{"learn":[2.35358251],"iteration":113,"passed_time":561.5171726,"remaining_time":1901.277444,"test":[2.426696998]},
{"learn":[2.352127678],"iteration":114,"passed_time":566.2802461,"remaining_time":1895.807781,"test":[2.425474503]},
{"learn":[2.350538308],"iteration":115,"passed_time":571.2469395,"remaining_time":1891.024351,"test":[2.424405559]},
{"learn":[2.349233176],"iteration":116,"passed_time":576.1564143,"remaining_time":1886.050484,"test":[2.423537479]},
{"learn":[2.347786479],"iteration":117,"passed_time":581.2844376,"remaining_time":1881.785213,"test":[2.422670803]},
{"learn":[2.346426356],"iteration":118,"passed_time":586.2463413,"remaining_time":1876.97358,"test":[2.421955445]},
{"learn":[2.345081085],"iteration":119,"passed_time":591.3320421,"remaining_time":1872.551467,"test":[2.421218193]},
{"learn":[2.34374567],"iteration":120,"passed_time":596.2966613,"remaining_time":1867.739129,"test":[2.420566603]},
{"learn":[2.342455576],"iteration":121,"passed_time":601.0808682,"remaining_time":1862.365313,"test":[2.419713513]},
{"learn":[2.341353534],"iteration":122,"passed_time":605.7918597,"remaining_time":1856.776676,"test":[2.419194171]},
{"learn":[2.340059067],"iteration":123,"passed_time":610.7052294,"remaining_time":1851.815857,"test":[2.418446126]},
{"learn":[2.338813203],"iteration":124,"passed_time":615.8197331,"remaining_time":1847.459199,"test":[2.417757907]},
{"learn":[2.337634952],"iteration":125,"passed_time":620.8563688,"remaining_time":1842.85938,"test":[2.417006727]},
{"learn":[2.336324881],"iteration":126,"passed_time":625.8501989,"remaining_time":1838.126962,"test":[2.416057295]},
{"learn":[2.335099651],"iteration":127,"passed_time":630.7743098,"remaining_time":1833.187838,"test":[2.415380566]},
{"learn":[2.333883368],"iteration":128,"passed_time":635.7963264,"remaining_time":1828.53052,"test":[2.41466933]},
{"learn":[2.3325096],"iteration":129,"passed_time":640.8817155,"remaining_time":1824.047959,"test":[2.413768104]},
{"learn":[2.331357066],"iteration":130,"passed_time":645.8275172,"remaining_time":1819.163006,"test":[2.413070298]},
{"learn":[2.330192295],"iteration":131,"passed_time":651.0303149,"remaining_time":1814.993605,"test":[2.4125035]},
{"learn":[2.329159685],"iteration":132,"passed_time":655.9105219,"remaining_time":1809.918508,"test":[2.411933815]},
{"learn":[2.327945495],"iteration":133,"passed_time":660.8555986,"remaining_time":1805.023501,"test":[2.411257029]},
{"learn":[2.326806313],"iteration":134,"passed_time":665.8259847,"remaining_time":1800.196181,"test":[2.410605396]},
{"learn":[2.325669895],"iteration":135,"passed_time":670.7311654,"remaining_time":1795.192237,"test":[2.410078053]},
{"learn":[2.324500623],"iteration":136,"passed_time":675.9116429,"remaining_time":1790.919171,"test":[2.409394005]},
{"learn":[2.323409008],"iteration":137,"passed_time":681.1552259,"remaining_time":1786.798491,"test":[2.408863093]},
{"learn":[2.322232922],"iteration":138,"passed_time":686.4881927,"remaining_time":1782.893795,"test":[2.408243138]},
{"learn":[2.321081624],"iteration":139,"passed_time":691.3975751,"remaining_time":1777.879479,"test":[2.407589957]},
{"learn":[2.320080625],"iteration":140,"passed_time":696.3709972,"remaining_time":1773.029702,"test":[2.406967546]},
{"learn":[2.319000562],"iteration":141,"passed_time":701.5074155,"remaining_time":1768.589118,"test":[2.406422946]},
{"learn":[2.318049164],"iteration":142,"passed_time":706.5879383,"remaining_time":1763.999259,"test":[2.405773192]},
{"learn":[2.31693529],"iteration":143,"passed_time":711.7595487,"remaining_time":1759.627773,"test":[2.405201863]},
{"learn":[2.315601625],"iteration":144,"passed_time":716.7849906,"remaining_time":1754.887391,"test":[2.404149853]},
{"learn":[2.314493267],"iteration":145,"passed_time":722.061758,"remaining_time":1750.752482,"test":[2.403552421]},
{"learn":[2.313123053],"iteration":146,"passed_time":726.7978438,"remaining_time":1745.303666,"test":[2.402696209]},
{"learn":[2.311945898],"iteration":147,"passed_time":731.5873055,"remaining_time":1739.991429,"test":[2.401881094]},
{"learn":[2.310815674],"iteration":148,"passed_time":736.5936973,"remaining_time":1735.197233,"test":[2.401223509]},
{"learn":[2.309819438],"iteration":149,"passed_time":741.4404935,"remaining_time":1730.027818,"test":[2.400671131]},
{"learn":[2.308829832],"iteration":150,"passed_time":746.5157996,"remaining_time":1725.390822,"test":[2.400089114]},
{"learn":[2.307703082],"iteration":151,"passed_time":751.6630998,"remaining_time":1720.912886,"test":[2.399565456]},
{"learn":[2.306655422],"iteration":152,"passed_time":756.5154136,"remaining_time":1715.75718,"test":[2.399003884]},
{"learn":[2.305214504],"iteration":153,"passed_time":761.4878951,"remaining_time":1710.875401,"test":[2.398064236]},
{"learn":[2.304160761],"iteration":154,"passed_time":767.0235632,"remaining_time":1707.245995,"test":[2.397480611]},
{"learn":[2.303076648],"iteration":155,"passed_time":772.2260701,"remaining_time":1702.857488,"test":[2.397071278]},
{"learn":[2.30186386],"iteration":156,"passed_time":777.3945257,"remaining_time":1698.384219,"test":[2.396448407]},
{"learn":[2.300908532],"iteration":157,"passed_time":782.2809127,"remaining_time":1693.291596,"test":[2.395993859]},
{"learn":[2.299991225],"iteration":158,"passed_time":786.4605708,"remaining_time":1686.685878,"test":[2.395561237]},
{"learn":[2.298954945],"iteration":159,"passed_time":790.9744353,"remaining_time":1680.820675,"test":[2.395052289]},
{"learn":[2.298030421],"iteration":160,"passed_time":795.6937487,"remaining_time":1675.40485,"test":[2.394495562]},
{"learn":[2.296980382],"iteration":161,"passed_time":799.9359785,"remaining_time":1669.002227,"test":[2.394015615]},
{"learn":[2.296031311],"iteration":162,"passed_time":804.2287324,"remaining_time":1662.73057,"test":[2.393494399]},
{"learn":[2.295106946],"iteration":163,"passed_time":808.4076118,"remaining_time":1656.249741,"test":[2.39301578]},
{"learn":[2.294076285],"iteration":164,"passed_time":812.6408283,"remaining_time":1649.907136,"test":[2.392433891]},
{"learn":[2.292605303],"iteration":165,"passed_time":816.9050019,"remaining_time":1643.652233,"test":[2.391443679]},
{"learn":[2.291590447],"iteration":166,"passed_time":821.4393075,"remaining_time":1637.959817,"test":[2.390777094]},
{"learn":[2.29060881],"iteration":167,"passed_time":825.792459,"remaining_time":1631.923193,"test":[2.39034119]},
{"learn":[2.289535951],"iteration":168,"passed_time":830.1831364,"remaining_time":1625.979989,"test":[2.389763305]},
{"learn":[2.288541269],"iteration":169,"passed_time":834.6667645,"remaining_time":1620.235484,"test":[2.389187404]},
{"learn":[2.287503747],"iteration":170,"passed_time":839.1483768,"remaining_time":1614.501848,"test":[2.388618965]},
{"learn":[2.286747467],"iteration":171,"passed_time":843.4170291,"remaining_time":1608.37666,"test":[2.388258125]},
{"learn":[2.28582141],"iteration":172,"passed_time":847.8021429,"remaining_time":1602.493068,"test":[2.387858907]},
{"learn":[2.284807777],"iteration":173,"passed_time":852.2156101,"remaining_time":1596.679821,"test":[2.38735491]},
{"learn":[2.28388251],"iteration":174,"passed_time":856.5654222,"remaining_time":1590.764356,"test":[2.386920062]},
{"learn":[2.282918221],"iteration":175,"passed_time":860.8913585,"remaining_time":1584.822728,"test":[2.386329935]},
{"learn":[2.282016511],"iteration":176,"passed_time":865.2741564,"remaining_time":1579.003122,"test":[2.385771448]},
{"learn":[2.281145464],"iteration":177,"passed_time":869.5787984,"remaining_time":1573.058276,"test":[2.385277107]},
{"learn":[2.2802284],"iteration":178,"passed_time":873.9879407,"remaining_time":1567.319156,"test":[2.384799377]},
{"learn":[2.279247812],"iteration":179,"passed_time":878.4846111,"remaining_time":1561.75042,"test":[2.384291898]},
{"learn":[2.278366641],"iteration":180,"passed_time":882.8657201,"remaining_time":1555.98986,"test":[2.383912634]},
{"learn":[2.277282456],"iteration":181,"passed_time":887.2134374,"remaining_time":1550.186116,"test":[2.383139881]},
{"learn":[2.276406391],"iteration":182,"passed_time":891.588526,"remaining_time":1544.445698,"test":[2.382700983]},
{"learn":[2.275455841],"iteration":183,"passed_time":895.9821241,"remaining_time":1538.751909,"test":[2.382068985]},
{"learn":[2.274651883],"iteration":184,"passed_time":900.3808123,"remaining_time":1533.080843,"test":[2.381706707]},
{"learn":[2.273778182],"iteration":185,"passed_time":904.8214053,"remaining_time":1527.4942,"test":[2.381266907]},
{"learn":[2.272709892],"iteration":186,"passed_time":909.2603869,"remaining_time":1521.917118,"test":[2.38073682]},
{"learn":[2.271793959],"iteration":187,"passed_time":913.7992353,"remaining_time":1516.51788,"test":[2.380523268]},
{"learn":[2.270942824],"iteration":188,"passed_time":918.2235116,"remaining_time":1510.939217,"test":[2.380092645]},
{"learn":[2.269988973],"iteration":189,"passed_time":922.7087621,"remaining_time":1505.472191,"test":[2.379581196]},
{"learn":[2.269095177],"iteration":190,"passed_time":927.2263858,"remaining_time":1500.067818,"test":[2.379252577]},
{"learn":[2.268141137],"iteration":191,"passed_time":931.685865,"remaining_time":1494.579408,"test":[2.378832833]},
{"learn":[2.267397611],"iteration":192,"passed_time":935.9502047,"remaining_time":1488.791258,"test":[2.378500032]},
{"learn":[2.266529478],"iteration":193,"passed_time":940.3087038,"remaining_time":1483.167337,"test":[2.378032898]},
{"learn":[2.265303779],"iteration":194,"passed_time":944.8455862,"remaining_time":1477.835404,"test":[2.377238063]},
{"learn":[2.264121195],"iteration":195,"passed_time":949.2911384,"remaining_time":1472.369929,"test":[2.376608805]},
{"learn":[2.263175521],"iteration":196,"passed_time":953.7371572,"remaining_time":1466.915526,"test":[2.376114756]},
{"learn":[2.262321448],"iteration":197,"passed_time":958.3033231,"remaining_time":1461.654564,"test":[2.375610142]},
{"learn":[2.261551009],"iteration":198,"passed_time":962.6323785,"remaining_time":1456.041939,"test":[2.375109679]},
{"learn":[2.260622203],"iteration":199,"passed_time":967.0822519,"remaining_time":1450.623378,"test":[2.374693882]},
{"learn":[2.259976664],"iteration":200,"passed_time":971.4880527,"remaining_time":1445.148894,"test":[2.3743761]},
{"learn":[2.25912225],"iteration":201,"passed_time":975.7890929,"remaining_time":1439.530444,"test":[2.374016906]},
{"learn":[2.25834207],"iteration":202,"passed_time":980.1504615,"remaining_time":1434.013237,"test":[2.373650744]},
{"learn":[2.25760322],"iteration":203,"passed_time":985.2986794,"remaining_time":1429.649064,"test":[2.373355149]},
{"learn":[2.256759306],"iteration":204,"passed_time":990.3284393,"remaining_time":1425.106779,"test":[2.373064555]},
{"learn":[2.255843117],"iteration":205,"passed_time":995.4516359,"remaining_time":1420.693111,"test":[2.37262285]},
{"learn":[2.255032001],"iteration":206,"passed_time":1000.25494,"remaining_time":1415.819795,"test":[2.372246022]},
{"learn":[2.254258398],"iteration":207,"passed_time":1005.09513,"remaining_time":1410.998933,"test":[2.371994835]},
{"learn":[2.253472594],"iteration":208,"passed_time":1009.859797,"remaining_time":1406.072732,"test":[2.371639568]},
{"learn":[2.252288775],"iteration":209,"passed_time":1014.899071,"remaining_time":1401.527289,"test":[2.370844174]},
{"learn":[2.25144375],"iteration":210,"passed_time":1019.763542,"remaining_time":1396.737743,"test":[2.370437948]},
{"learn":[2.250540467],"iteration":211,"passed_time":1024.6946,"remaining_time":1392.037947,"test":[2.37003272]},
{"learn":[2.249738516],"iteration":212,"passed_time":1029.553305,"remaining_time":1387.23849,"test":[2.369592652]},
{"learn":[2.248821862],"iteration":213,"passed_time":1034.424514,"remaining_time":1382.455192,"test":[2.369087622]},
{"learn":[2.247974903],"iteration":214,"passed_time":1039.46921,"remaining_time":1377.901046,"test":[2.368768708]},
{"learn":[2.247200626],"iteration":215,"passed_time":1044.441241,"remaining_time":1373.246817,"test":[2.368410695]},
{"learn":[2.246431997],"iteration":216,"passed_time":1049.276875,"remaining_time":1368.411778,"test":[2.368112138]},
{"learn":[2.245514553],"iteration":217,"passed_time":1054.287938,"remaining_time":1363.803663,"test":[2.36764027]},
{"learn":[2.244665726],"iteration":218,"passed_time":1059.116686,"remaining_time":1358.957939,"test":[2.367310819]},
{"learn":[2.243870933],"iteration":219,"passed_time":1064.058488,"remaining_time":1354.256257,"test":[2.366880925]},
{"learn":[2.243152231],"iteration":220,"passed_time":1069.003729,"remaining_time":1349.556744,"test":[2.366698332]},
{"learn":[2.242398145],"iteration":221,"passed_time":1073.816179,"remaining_time":1344.688728,"test":[2.366435492]},
{"learn":[2.241368359],"iteration":222,"passed_time":1078.830489,"remaining_time":1340.071952,"test":[2.365767502]},
{"learn":[2.240697179],"iteration":223,"passed_time":1083.580972,"remaining_time":1335.126554,"test":[2.36552296]},
{"learn":[2.239848038],"iteration":224,"passed_time":1088.778031,"remaining_time":1330.728704,"test":[2.365231999]},
{"learn":[2.239096682],"iteration":225,"passed_time":1093.723113,"remaining_time":1326.018288,"test":[2.365006658]},
{"learn":[2.238168172],"iteration":226,"passed_time":1098.660515,"remaining_time":1321.296567,"test":[2.364663037]},
{"learn":[2.237334712],"iteration":227,"passed_time":1103.667479,"remaining_time":1316.65594,"test":[2.364239816]},
{"learn":[2.236581012],"iteration":228,"passed_time":1108.620222,"remaining_time":1311.947949,"test":[2.363856168]},
{"learn":[2.235741236],"iteration":229,"passed_time":1113.620322,"remaining_time":1307.293421,"test":[2.363579773]},
{"learn":[2.234980056],"iteration":230,"passed_time":1118.510917,"remaining_time":1302.508384,"test":[2.363316263]},
{"learn":[2.234154137],"iteration":231,"passed_time":1123.309349,"remaining_time":1297.615972,"test":[2.3629431]},
{"learn":[2.23332316],"iteration":232,"passed_time":1128.084781,"remaining_time":1292.698011,"test":[2.362706655]},
{"learn":[2.232496187],"iteration":233,"passed_time":1133.03804,"remaining_time":1287.983414,"test":[2.362405079]},
{"learn":[2.231784111],"iteration":234,"passed_time":1137.958117,"remaining_time":1283.229366,"test":[2.362079568]},
{"learn":[2.230980053],"iteration":235,"passed_time":1142.876507,"remaining_time":1278.472025,"test":[2.361551249]},
{"learn":[2.230313786],"iteration":236,"passed_time":1147.718873,"remaining_time":1273.628961,"test":[2.3612613]},
{"learn":[2.229612063],"iteration":237,"passed_time":1152.78753,"remaining_time":1269.035012,"test":[2.360879292]},
{"learn":[2.228735143],"iteration":238,"passed_time":1157.949722,"remaining_time":1264.539236,"test":[2.360513025]},
{"learn":[2.228111728],"iteration":239,"passed_time":1162.681193,"remaining_time":1259.571292,"test":[2.360128761]},
{"learn":[2.227389223],"iteration":240,"passed_time":1167.466622,"remaining_time":1254.6633,"test":[2.359795709]},
{"learn":[2.226612292],"iteration":241,"passed_time":1172.622005,"remaining_time":1250.150732,"test":[2.359571948]},
{"learn":[2.22564342],"iteration":242,"passed_time":1177.784537,"remaining_time":1245.640436,"test":[2.359037012]},
{"learn":[2.224978953],"iteration":243,"passed_time":1182.713667,"remaining_time":1240.879913,"test":[2.358781796]},
{"learn":[2.224204034],"iteration":244,"passed_time":1187.920427,"remaining_time":1236.406975,"test":[2.358372202]},
{"learn":[2.223421373],"iteration":245,"passed_time":1192.956647,"remaining_time":1231.751985,"test":[2.357857034]},
{"learn":[2.22261726],"iteration":246,"passed_time":1197.915571,"remaining_time":1227.014735,"test":[2.357636085]},
{"learn":[2.221795654],"iteration":247,"passed_time":1202.948424,"remaining_time":1222.350818,"test":[2.357311583]},
{"learn":[2.221030422],"iteration":248,"passed_time":1207.980047,"remaining_time":1217.682698,"test":[2.356978234]},
{"learn":[2.220241081],"iteration":249,"passed_time":1212.871185,"remaining_time":1212.871185,"test":[2.356725209]},
{"learn":[2.219572018],"iteration":250,"passed_time":1217.832005,"remaining_time":1208.128164,"test":[2.356434552]},
{"learn":[2.218753767],"iteration":251,"passed_time":1222.753214,"remaining_time":1203.344433,"test":[2.35617294]},
{"learn":[2.218063117],"iteration":252,"passed_time":1227.660971,"remaining_time":1198.546482,"test":[2.356080853]},
{"learn":[2.217075639],"iteration":253,"passed_time":1232.577604,"remaining_time":1193.756262,"test":[2.355539742]},
{"learn":[2.21651679],"iteration":254,"passed_time":1237.436769,"remaining_time":1188.909836,"test":[2.355291855]},
{"learn":[2.215732256],"iteration":255,"passed_time":1242.717815,"remaining_time":1184.465418,"test":[2.35504461]},
{"learn":[2.214984151],"iteration":256,"passed_time":1247.709358,"remaining_time":1179.740755,"test":[2.354763007]},
{"learn":[2.214268295],"iteration":257,"passed_time":1251.901207,"remaining_time":1174.263923,"test":[2.354429798]},
{"learn":[2.213578868],"iteration":258,"passed_time":1256.118199,"remaining_time":1168.82041,"test":[2.354079024]},
{"learn":[2.212886202],"iteration":259,"passed_time":1260.38122,"remaining_time":1163.428819,"test":[2.353877039]},
{"learn":[2.212116083],"iteration":260,"passed_time":1264.607486,"remaining_time":1158.012219,"test":[2.353498254]},
{"learn":[2.211376987],"iteration":261,"passed_time":1268.84888,"remaining_time":1152.618448,"test":[2.353309666]},
{"learn":[2.210630227],"iteration":262,"passed_time":1273.060129,"remaining_time":1147.206276,"test":[2.353032082]},
{"learn":[2.209871554],"iteration":263,"passed_time":1277.398507,"remaining_time":1141.916847,"test":[2.352735957]},
{"learn":[2.209009302],"iteration":264,"passed_time":1281.646759,"remaining_time":1136.554673,"test":[2.352287062]},
{"learn":[2.20821186],"iteration":265,"passed_time":1285.79419,"remaining_time":1131.112182,"test":[2.352017214]},
{"learn":[2.207385807],"iteration":266,"passed_time":1290.093761,"remaining_time":1125.812159,"test":[2.351885742]},
{"learn":[2.206628026],"iteration":267,"passed_time":1294.359115,"remaining_time":1120.48998,"test":[2.351574043]},
{"learn":[2.206026419],"iteration":268,"passed_time":1298.53119,"remaining_time":1115.095557,"test":[2.351452758]},
{"learn":[2.20530092],"iteration":269,"passed_time":1302.810844,"remaining_time":1109.80183,"test":[2.351242082]},
{"learn":[2.20449427],"iteration":270,"passed_time":1307.097047,"remaining_time":1104.521121,"test":[2.351019666]},
{"learn":[2.203636835],"iteration":271,"passed_time":1311.324744,"remaining_time":1099.198682,"test":[2.350676057]},
{"learn":[2.202944976],"iteration":272,"passed_time":1315.576247,"remaining_time":1093.904059,"test":[2.350354103]},
{"learn":[2.202162936],"iteration":273,"passed_time":1319.761248,"remaining_time":1088.562197,"test":[2.349831567]},
{"learn":[2.20153278],"iteration":274,"passed_time":1323.858166,"remaining_time":1083.156681,"test":[2.349431812]},
{"learn":[2.200799668],"iteration":275,"passed_time":1328.062305,"remaining_time":1077.847668,"test":[2.349305885]},
{"learn":[2.200023651],"iteration":276,"passed_time":1332.309426,"remaining_time":1072.581235,"test":[2.349042612]},
{"learn":[2.199200386],"iteration":277,"passed_time":1336.602982,"remaining_time":1067.359215,"test":[2.348718531]},
{"learn":[2.198421007],"iteration":278,"passed_time":1340.856795,"remaining_time":1062.112371,"test":[2.348410613]},
{"learn":[2.197577311],"iteration":279,"passed_time":1345.165786,"remaining_time":1056.915975,"test":[2.347855994]},
{"learn":[2.196815445],"iteration":280,"passed_time":1349.336127,"remaining_time":1051.617835,"test":[2.347426576]},
{"learn":[2.196158452],"iteration":281,"passed_time":1353.699996,"remaining_time":1046.477302,"test":[2.347188135]},
{"learn":[2.195454479],"iteration":282,"passed_time":1357.876939,"remaining_time":1041.198925,"test":[2.346895392]},
{"learn":[2.194717216],"iteration":283,"passed_time":1362.193316,"remaining_time":1036.034353,"test":[2.346625279]},
{"learn":[2.193944189],"iteration":284,"passed_time":1366.569062,"remaining_time":1030.920521,"test":[2.34640858]},
{"learn":[2.193175294],"iteration":285,"passed_time":1370.906761,"remaining_time":1025.783381,"test":[2.346093702]},
{"learn":[2.192509578],"iteration":286,"passed_time":1375.113775,"remaining_time":1020.554823,"test":[2.345835977]},
{"learn":[2.191777289],"iteration":287,"passed_time":1379.383541,"remaining_time":1015.379551,"test":[2.345547938]},
{"learn":[2.191017829],"iteration":288,"passed_time":1383.604481,"remaining_time":1010.174898,"test":[2.34524662]},
{"learn":[2.190310492],"iteration":289,"passed_time":1387.842194,"remaining_time":1004.989175,"test":[2.344905596]},
{"learn":[2.189537366],"iteration":290,"passed_time":1392.631005,"remaining_time":1000.205773,"test":[2.344531657]},
{"learn":[2.188861489],"iteration":291,"passed_time":1397.473382,"remaining_time":995.4604913,"test":[2.344326503]},
{"learn":[2.188105353],"iteration":292,"passed_time":1402.70356,"remaining_time":990.988522,"test":[2.343946814]},
{"learn":[2.187362127],"iteration":293,"passed_time":1407.453792,"remaining_time":986.1751057,"test":[2.343769418]},
{"learn":[2.186547707],"iteration":294,"passed_time":1412.118719,"remaining_time":981.3028389,"test":[2.343394643]},
{"learn":[2.18595246],"iteration":295,"passed_time":1416.995162,"remaining_time":976.5777469,"test":[2.343227759]},
{"learn":[2.185236596],"iteration":296,"passed_time":1421.811392,"remaining_time":971.8104798,"test":[2.34294964]},
{"learn":[2.184373466],"iteration":297,"passed_time":1426.736063,"remaining_time":967.1163918,"test":[2.342368826]},
{"learn":[2.183804163],"iteration":298,"passed_time":1431.526259,"remaining_time":962.3303617,"test":[2.342109428]},
{"learn":[2.183045247],"iteration":299,"passed_time":1436.489052,"remaining_time":957.6593682,"test":[2.34192441]},
{"learn":[2.182397524],"iteration":300,"passed_time":1441.373659,"remaining_time":952.9347445,"test":[2.341799391]},
{"learn":[2.181699924],"iteration":301,"passed_time":1446.143606,"remaining_time":948.1338872,"test":[2.341644071]},
{"learn":[2.181131628],"iteration":302,"passed_time":1450.708429,"remaining_time":943.1998695,"test":[2.341421133]},
{"learn":[2.180066512],"iteration":303,"passed_time":1455.44985,"remaining_time":938.3821403,"test":[2.340731279]},
{"learn":[2.17938962],"iteration":304,"passed_time":1460.531475,"remaining_time":933.7824186,"test":[2.340633866]},
{"learn":[2.178441927],"iteration":305,"passed_time":1465.61821,"remaining_time":929.182787,"test":[2.340139142]},
{"learn":[2.177778935],"iteration":306,"passed_time":1470.516969,"remaining_time":924.4618079,"test":[2.339875617]},
{"learn":[2.177127179],"iteration":307,"passed_time":1474.844919,"remaining_time":919.3838455,"test":[2.339686205]},
{"learn":[2.176320606],"iteration":308,"passed_time":1479.076168,"remaining_time":914.2509644,"test":[2.339171635]},
{"learn":[2.175602304],"iteration":309,"passed_time":1483.472226,"remaining_time":909.2249125,"test":[2.33897]},
{"learn":[2.175015797],"iteration":310,"passed_time":1487.593688,"remaining_time":904.0360356,"test":[2.338779804]},
{"learn":[2.174451368],"iteration":311,"passed_time":1491.826079,"remaining_time":898.9208427,"test":[2.33855411]},
{"learn":[2.173880633],"iteration":312,"passed_time":1496.511981,"remaining_time":894.0822378,"test":[2.338356599]},
{"learn":[2.173143069],"iteration":313,"passed_time":1501.478667,"remaining_time":889.4109303,"test":[2.337982317]},
{"learn":[2.172430689],"iteration":314,"passed_time":1505.750669,"remaining_time":884.3297579,"test":[2.337674022]},
{"learn":[2.171758998],"iteration":315,"passed_time":1509.977,"remaining_time":879.2271141,"test":[2.337430439]},
{"learn":[2.170863109],"iteration":316,"passed_time":1514.327894,"remaining_time":874.201907,"test":[2.336971002]},
{"learn":[2.170239838],"iteration":317,"passed_time":1518.408743,"remaining_time":869.0263873,"test":[2.336771904]},
{"learn":[2.169473799],"iteration":318,"passed_time":1522.968781,"remaining_time":864.1296217,"test":[2.336342084]},
{"learn":[2.168946689],"iteration":319,"passed_time":1527.164859,"remaining_time":859.0302333,"test":[2.336168157]},
{"learn":[2.168431965],"iteration":320,"passed_time":1531.378499,"remaining_time":853.946266,"test":[2.336030658]},
{"learn":[2.167496381],"iteration":321,"passed_time":1535.656503,"remaining_time":848.9032841,"test":[2.33546423]},
{"learn":[2.166664715],"iteration":322,"passed_time":1539.959414,"remaining_time":843.878688,"test":[2.335142953]},
{"learn":[2.165998256],"iteration":323,"passed_time":1544.216008,"remaining_time":838.8333872,"test":[2.33487444]},
{"learn":[2.165304061],"iteration":324,"passed_time":1548.385883,"remaining_time":833.7462444,"test":[2.334634583]},
{"learn":[2.164487869],"iteration":325,"passed_time":1553.319221,"remaining_time":829.0722223,"test":[2.334364804]},
{"learn":[2.163798085],"iteration":326,"passed_time":1557.574759,"remaining_time":824.0380224,"test":[2.333951655]},
{"learn":[2.163151801],"iteration":327,"passed_time":1561.886274,"remaining_time":819.0379244,"test":[2.333799262]},
{"learn":[2.162462016],"iteration":328,"passed_time":1566.151502,"remaining_time":814.0179538,"test":[2.333579592]},
{"learn":[2.16170293],"iteration":329,"passed_time":1570.41021,"remaining_time":808.999199,"test":[2.333216571]},
{"learn":[2.161064931],"iteration":330,"passed_time":1574.706514,"remaining_time":804.0042321,"test":[2.333072144]},
{"learn":[2.160358406],"iteration":331,"passed_time":1579.004688,"remaining_time":799.0144206,"test":[2.332849664]},
{"learn":[2.159686174],"iteration":332,"passed_time":1583.3397,"remaining_time":794.0472369,"test":[2.332650041]},
{"learn":[2.158968324],"iteration":333,"passed_time":1587.662057,"remaining_time":789.0775494,"test":[2.332367884]},
{"learn":[2.158251823],"iteration":334,"passed_time":1592.019009,"remaining_time":784.1287654,"test":[2.332162932]},
{"learn":[2.157704184],"iteration":335,"passed_time":1596.181698,"remaining_time":779.088686,"test":[2.331996492]},
{"learn":[2.157134323],"iteration":336,"passed_time":1600.344712,"remaining_time":774.0539706,"test":[2.331744985]},
{"learn":[2.156417417],"iteration":337,"passed_time":1604.596401,"remaining_time":769.0669141,"test":[2.331498392]},
{"learn":[2.155732104],"iteration":338,"passed_time":1608.79318,"remaining_time":764.0581182,"test":[2.331304287]},
{"learn":[2.155122231],"iteration":339,"passed_time":1613.009271,"remaining_time":759.0631864,"test":[2.331108721]},
{"learn":[2.154626851],"iteration":340,"passed_time":1617.131048,"remaining_time":754.0288464,"test":[2.330964239]},
{"learn":[2.153977475],"iteration":341,"passed_time":1621.294809,"remaining_time":749.0192393,"test":[2.330834314]},
{"learn":[2.153299584],"iteration":342,"passed_time":1625.481521,"remaining_time":744.0250692,"test":[2.330629218]},
{"learn":[2.152731969],"iteration":343,"passed_time":1629.668778,"remaining_time":739.0358413,"test":[2.330532402]},
{"learn":[2.152088351],"iteration":344,"passed_time":1633.880192,"remaining_time":734.0621151,"test":[2.330373844]},
{"learn":[2.151460548],"iteration":345,"passed_time":1638.026622,"remaining_time":729.0638724,"test":[2.330247099]},
{"learn":[2.150926125],"iteration":346,"passed_time":1642.101049,"remaining_time":724.038791,"test":[2.329961823]},
{"learn":[2.15035131],"iteration":347,"passed_time":1646.23676,"remaining_time":719.0459413,"test":[2.32982154]},
{"learn":[2.149647025],"iteration":348,"passed_time":1650.474906,"remaining_time":714.1023231,"test":[2.329696494]},
{"learn":[2.14915372],"iteration":349,"passed_time":1654.615482,"remaining_time":709.1209207,"test":[2.329444701]},
{"learn":[2.1485702],"iteration":350,"passed_time":1658.757662,"remaining_time":704.1449905,"test":[2.329291573]},
{"learn":[2.147932316],"iteration":351,"passed_time":1662.966205,"remaining_time":699.2016997,"test":[2.329054849]},
{"learn":[2.147180175],"iteration":352,"passed_time":1667.254362,"remaining_time":694.2957258,"test":[2.328844437]},
{"learn":[2.146563275],"iteration":353,"passed_time":1671.40127,"remaining_time":689.334987,"test":[2.328693983]},
{"learn":[2.145707345],"iteration":354,"passed_time":1675.562456,"remaining_time":684.3846651,"test":[2.328201573]},
{"learn":[2.145037014],"iteration":355,"passed_time":1679.813874,"remaining_time":679.4752748,"test":[2.328015449]},
{"learn":[2.1441325],"iteration":356,"passed_time":1683.997001,"remaining_time":674.5422162,"test":[2.327468504]},
{"learn":[2.143518435],"iteration":357,"passed_time":1688.198356,"remaining_time":669.6205768,"test":[2.327258335]},
{"learn":[2.142932655],"iteration":358,"passed_time":1692.382845,"remaining_time":664.6963262,"test":[2.327112414]},
{"learn":[2.142303861],"iteration":359,"passed_time":1696.638965,"remaining_time":659.804042,"test":[2.32690982]},
{"learn":[2.141625713],"iteration":360,"passed_time":1700.846596,"remaining_time":654.8966116,"test":[2.326643985]},
{"learn":[2.141028911],"iteration":361,"passed_time":1705.062582,"remaining_time":649.9962329,"test":[2.326412121]},
{"learn":[2.140234969],"iteration":362,"passed_time":1709.49367,"remaining_time":645.1808065,"test":[2.326136238]},
{"learn":[2.139567201],"iteration":363,"passed_time":1713.824629,"remaining_time":640.3300813,"test":[2.32608784]},
{"learn":[2.13904315],"iteration":364,"passed_time":1717.990713,"remaining_time":635.4212227,"test":[2.325914221]},
{"learn":[2.138454936],"iteration":365,"passed_time":1722.229746,"remaining_time":630.543131,"test":[2.325815139]},
{"learn":[2.13788625],"iteration":366,"passed_time":1726.390133,"remaining_time":625.640021,"test":[2.325649223]},
{"learn":[2.137259918],"iteration":367,"passed_time":1730.66274,"remaining_time":620.7812001,"test":[2.325511241]},
{"learn":[2.13667845],"iteration":368,"passed_time":1734.815588,"remaining_time":615.8830408,"test":[2.32538565]},
{"learn":[2.135918177],"iteration":369,"passed_time":1739.158514,"remaining_time":611.055694,"test":[2.325139419]},
{"learn":[2.135346951],"iteration":370,"passed_time":1743.347545,"remaining_time":606.1774482,"test":[2.325005527]},
{"learn":[2.134721965],"iteration":371,"passed_time":1747.605922,"remaining_time":601.3267687,"test":[2.324795541]},
{"learn":[2.134251706],"iteration":372,"passed_time":1751.74183,"remaining_time":596.4375667,"test":[2.324606049]},
{"learn":[2.133554068],"iteration":373,"passed_time":1756.018028,"remaining_time":591.5996564,"test":[2.324357111]},
{"learn":[2.132814451],"iteration":374,"passed_time":1760.33023,"remaining_time":586.7767433,"test":[2.324144353]},
{"learn":[2.132238161],"iteration":375,"passed_time":1764.533545,"remaining_time":581.9206373,"test":[2.324003869]},
{"learn":[2.131432975],"iteration":376,"passed_time":1768.835334,"remaining_time":577.1001221,"test":[2.323770642]},
{"learn":[2.130882394],"iteration":377,"passed_time":1773.052032,"remaining_time":572.2548887,"test":[2.323544657]},
{"learn":[2.130194352],"iteration":378,"passed_time":1777.483035,"remaining_time":567.481391,"test":[2.323275142]},
{"learn":[2.129592492],"iteration":379,"passed_time":1781.787822,"remaining_time":562.6698385,"test":[2.323147502]},
{"learn":[2.12894923],"iteration":380,"passed_time":1786.150225,"remaining_time":557.8789416,"test":[2.322958559]},
{"learn":[2.127974033],"iteration":381,"passed_time":1790.621656,"remaining_time":553.1239669,"test":[2.322551792]},
{"learn":[2.127556218],"iteration":382,"passed_time":1794.762454,"remaining_time":548.2694703,"test":[2.322407215]},
{"learn":[2.126819143],"iteration":383,"passed_time":1799.020034,"remaining_time":543.4539687,"test":[2.322198675]},
{"learn":[2.126132787],"iteration":384,"passed_time":1803.306203,"remaining_time":538.6499047,"test":[2.322032445]},
{"learn":[2.125537641],"iteration":385,"passed_time":1807.521053,"remaining_time":533.8274612,"test":[2.321898698]},
{"learn":[2.124889812],"iteration":386,"passed_time":1811.755099,"remaining_time":529.0137626,"test":[2.321768723]},
{"learn":[2.124164602],"iteration":387,"passed_time":1816.144486,"remaining_time":524.2478929,"test":[2.32148325]},
{"learn":[2.123515686],"iteration":388,"passed_time":1820.482276,"remaining_time":519.4692355,"test":[2.321266187]},
{"learn":[2.122707561],"iteration":389,"passed_time":1824.763245,"remaining_time":514.6768126,"test":[2.320975007]},
{"learn":[2.121986935],"iteration":390,"passed_time":1829.074057,"remaining_time":509.8953252,"test":[2.320862102]},
{"learn":[2.121476868],"iteration":391,"passed_time":1833.161883,"remaining_time":505.0548045,"test":[2.320560285]},
{"learn":[2.120940044],"iteration":392,"passed_time":1837.440325,"remaining_time":500.2700123,"test":[2.320292352]},
{"learn":[2.12017166],"iteration":393,"passed_time":1841.744052,"remaining_time":495.4945927,"test":[2.319863726]},
{"learn":[2.119561839],"iteration":394,"passed_time":1846.037755,"remaining_time":490.718897,"test":[2.31960458]},
{"learn":[2.118846915],"iteration":395,"passed_time":1850.434586,"remaining_time":485.9727194,"test":[2.319310833]},
{"learn":[2.118158164],"iteration":396,"passed_time":1854.898714,"remaining_time":481.2457621,"test":[2.31911702]},
{"learn":[2.117449078],"iteration":397,"passed_time":1859.256918,"remaining_time":476.492979,"test":[2.318886927]},
{"learn":[2.116787991],"iteration":398,"passed_time":1863.615643,"remaining_time":471.7423057,"test":[2.318732491]},
{"learn":[2.116209134],"iteration":399,"passed_time":1867.919999,"remaining_time":466.9799997,"test":[2.31859386]},
{"learn":[2.115622806],"iteration":400,"passed_time":1872.210766,"remaining_time":462.216623,"test":[2.318286917]},
{"learn":[2.115043255],"iteration":401,"passed_time":1876.429936,"remaining_time":457.4381436,"test":[2.31795966]},
{"learn":[2.114505173],"iteration":402,"passed_time":1880.682643,"remaining_time":452.670512,"test":[2.317805155]},
{"learn":[2.113791094],"iteration":403,"passed_time":1884.846072,"remaining_time":447.8842152,"test":[2.317437224]},
{"learn":[2.112915149],"iteration":404,"passed_time":1889.042595,"remaining_time":443.1087568,"test":[2.317025236]},
{"learn":[2.112200743],"iteration":405,"passed_time":1893.325622,"remaining_time":438.3561785,"test":[2.316775532]},
{"learn":[2.111563873],"iteration":406,"passed_time":1897.66229,"remaining_time":433.6181646,"test":[2.3166779]},
{"learn":[2.110792154],"iteration":407,"passed_time":1901.91846,"remaining_time":428.8639665,"test":[2.316315593]},
{"learn":[2.110083837],"iteration":408,"passed_time":1906.07621,"remaining_time":424.0903059,"test":[2.315968193]},
{"learn":[2.109644124],"iteration":409,"passed_time":1910.17949,"remaining_time":419.307693,"test":[2.315787783]},
{"learn":[2.109014529],"iteration":410,"passed_time":1914.445608,"remaining_time":414.5636474,"test":[2.315651749]},
{"learn":[2.108337286],"iteration":411,"passed_time":1918.720076,"remaining_time":409.8237056,"test":[2.31547404]},
{"learn":[2.107840796],"iteration":412,"passed_time":1922.982547,"remaining_time":405.0834905,"test":[2.315330729]},
{"learn":[2.10739805],"iteration":413,"passed_time":1927.206468,"remaining_time":400.3375755,"test":[2.315226854]},
{"learn":[2.106792357],"iteration":414,"passed_time":1931.544507,"remaining_time":395.6175495,"test":[2.314953292]},
{"learn":[2.106047775],"iteration":415,"passed_time":1936.096851,"remaining_time":390.9426334,"test":[2.314708598]},
{"learn":[2.105316935],"iteration":416,"passed_time":1940.54366,"remaining_time":386.2472992,"test":[2.314550789]},
{"learn":[2.104732169],"iteration":417,"passed_time":1944.896251,"remaining_time":381.5346712,"test":[2.314420704]},
{"learn":[2.104114711],"iteration":418,"passed_time":1949.326349,"remaining_time":376.8387453,"test":[2.314201982]},
{"learn":[2.103720545],"iteration":419,"passed_time":1953.509851,"remaining_time":372.0971145,"test":[2.314067784]},
{"learn":[2.103049989],"iteration":420,"passed_time":1957.767966,"remaining_time":367.3721361,"test":[2.313659861]},
{"learn":[2.102317159],"iteration":421,"passed_time":1962.068681,"remaining_time":362.6572444,"test":[2.313473881]},
{"learn":[2.101653061],"iteration":422,"passed_time":1966.342793,"remaining_time":357.9394683,"test":[2.313320546]},
{"learn":[2.101019392],"iteration":423,"passed_time":1970.711733,"remaining_time":353.2407823,"test":[2.31306837]},
{"learn":[2.100223824],"iteration":424,"passed_time":1974.938124,"remaining_time":348.5184924,"test":[2.31268047]},
{"learn":[2.099620984],"iteration":425,"passed_time":1979.174438,"remaining_time":343.8002545,"test":[2.312354498]},
{"learn":[2.098995669],"iteration":426,"passed_time":1983.33917,"remaining_time":339.0720361,"test":[2.312270372]},
{"learn":[2.098097827],"iteration":427,"passed_time":1987.607829,"remaining_time":334.3639338,"test":[2.311974112]},
{"learn":[2.09743471],"iteration":428,"passed_time":1991.709304,"remaining_time":329.6302111,"test":[2.311755262]},
{"learn":[2.096603998],"iteration":429,"passed_time":1996.004958,"remaining_time":324.9310397,"test":[2.311386047]},
{"learn":[2.09580052],"iteration":430,"passed_time":2000.256258,"remaining_time":320.2266399,"test":[2.311193736]},
{"learn":[2.095056912],"iteration":431,"passed_time":2004.478549,"remaining_time":315.5197715,"test":[2.311020057]},
{"learn":[2.094237056],"iteration":432,"passed_time":2008.771011,"remaining_time":310.8259993,"test":[2.310765951]},
{"learn":[2.093698141],"iteration":433,"passed_time":2012.870807,"remaining_time":306.1047772,"test":[2.3104922]},
{"learn":[2.092988438],"iteration":434,"passed_time":2017.093105,"remaining_time":301.4047168,"test":[2.310200356]},
{"learn":[2.092339463],"iteration":435,"passed_time":2021.238053,"remaining_time":296.695494,"test":[2.309961574]},
{"learn":[2.091774733],"iteration":436,"passed_time":2025.296979,"remaining_time":291.9764523,"test":[2.309544882]},
{"learn":[2.091059049],"iteration":437,"passed_time":2029.456732,"remaining_time":287.2746973,"test":[2.309389243]},
{"learn":[2.090539179],"iteration":438,"passed_time":2033.626707,"remaining_time":282.5768317,"test":[2.309238978]},
{"learn":[2.089879798],"iteration":439,"passed_time":2037.910464,"remaining_time":277.8968814,"test":[2.309070702]},
{"learn":[2.089157057],"iteration":440,"passed_time":2042.331042,"remaining_time":273.2370329,"test":[2.308787575]},
{"learn":[2.088473086],"iteration":441,"passed_time":2046.482217,"remaining_time":268.5429154,"test":[2.308638553]},
{"learn":[2.087728826],"iteration":442,"passed_time":2050.765558,"remaining_time":263.8682547,"test":[2.308476118]},
{"learn":[2.087172076],"iteration":443,"passed_time":2054.960869,"remaining_time":259.1842537,"test":[2.308292531]},
{"learn":[2.086592982],"iteration":444,"passed_time":2059.153324,"remaining_time":254.5020962,"test":[2.308137988]},
{"learn":[2.086019646],"iteration":445,"passed_time":2063.303287,"remaining_time":249.8169899,"test":[2.307946741]},
{"learn":[2.085392446],"iteration":446,"passed_time":2067.429035,"remaining_time":245.1314068,"test":[2.307836563]},
{"learn":[2.084433694],"iteration":447,"passed_time":2071.710343,"remaining_time":240.4663791,"test":[2.307287427]},
{"learn":[2.083697013],"iteration":448,"passed_time":2075.937611,"remaining_time":235.7969224,"test":[2.307123819]},
{"learn":[2.083077333],"iteration":449,"passed_time":2080.145072,"remaining_time":231.1272302,"test":[2.306961855]},
{"learn":[2.082331331],"iteration":450,"passed_time":2084.51315,"remaining_time":226.4770384,"test":[2.306872718]},
{"learn":[2.081722879],"iteration":451,"passed_time":2088.787584,"remaining_time":221.8181506,"test":[2.306662762]},
{"learn":[2.081148747],"iteration":452,"passed_time":2093.070659,"remaining_time":217.1618565,"test":[2.306459102]},
{"learn":[2.080459429],"iteration":453,"passed_time":2097.356226,"remaining_time":212.507459,"test":[2.306142525]},
{"learn":[2.079932858],"iteration":454,"passed_time":2101.588202,"remaining_time":207.8493826,"test":[2.305972578]},
{"learn":[2.079295521],"iteration":455,"passed_time":2105.852841,"remaining_time":203.1963267,"test":[2.305786055]},
{"learn":[2.078573963],"iteration":456,"passed_time":2110.168096,"remaining_time":198.5497334,"test":[2.305560997]},
{"learn":[2.077890473],"iteration":457,"passed_time":2114.454138,"remaining_time":193.9019079,"test":[2.305329145]},
{"learn":[2.077207897],"iteration":458,"passed_time":2118.778645,"remaining_time":189.2590946,"test":[2.305003115]},
{"learn":[2.076620479],"iteration":459,"passed_time":2123.03412,"remaining_time":184.6116626,"test":[2.304855528]},
{"learn":[2.07583936],"iteration":460,"passed_time":2127.309725,"remaining_time":179.967634,"test":[2.304460457]},
{"learn":[2.075184143],"iteration":461,"passed_time":2131.667726,"remaining_time":175.3319774,"test":[2.304244509]},
{"learn":[2.074560999],"iteration":462,"passed_time":2135.941828,"remaining_time":170.6908156,"test":[2.303950896]},
{"learn":[2.074042017],"iteration":463,"passed_time":2140.180579,"remaining_time":166.0484932,"test":[2.303747311]},
{"learn":[2.073350196],"iteration":464,"passed_time":2144.53148,"remaining_time":161.416348,"test":[2.303511798]},
{"learn":[2.072672864],"iteration":465,"passed_time":2148.911112,"remaining_time":156.787506,"test":[2.30331632]},
{"learn":[2.071726579],"iteration":466,"passed_time":2153.426882,"remaining_time":152.1693514,"test":[2.302859835]},
{"learn":[2.071089354],"iteration":467,"passed_time":2157.744931,"remaining_time":147.538115,"test":[2.302645128]},
{"learn":[2.070465189],"iteration":468,"passed_time":2162.042387,"remaining_time":142.9068529,"test":[2.302447386]},
{"learn":[2.06969664],"iteration":469,"passed_time":2166.525085,"remaining_time":138.2888352,"test":[2.302302339]},
{"learn":[2.068980019],"iteration":470,"passed_time":2170.828152,"remaining_time":133.6603321,"test":[2.302071577]},
{"learn":[2.06798807],"iteration":471,"passed_time":2175.163568,"remaining_time":129.0351269,"test":[2.301548887]},
{"learn":[2.067222147],"iteration":472,"passed_time":2179.49452,"remaining_time":124.4108923,"test":[2.301281227]},
{"learn":[2.066372249],"iteration":473,"passed_time":2183.894112,"remaining_time":119.7916601,"test":[2.301106269]},
{"learn":[2.065818903],"iteration":474,"passed_time":2188.123951,"remaining_time":115.1644185,"test":[2.300785201]},
{"learn":[2.065223181],"iteration":475,"passed_time":2192.395399,"remaining_time":110.5409445,"test":[2.30059601]},
{"learn":[2.064534499],"iteration":476,"passed_time":2196.660116,"remaining_time":105.918622,"test":[2.300353978]},
{"learn":[2.063765919],"iteration":477,"passed_time":2200.963316,"remaining_time":101.2995668,"test":[2.300006558]},
{"learn":[2.063233248],"iteration":478,"passed_time":2205.153236,"remaining_time":96.67686422,"test":[2.299920584]},
{"learn":[2.062434183],"iteration":479,"passed_time":2209.429802,"remaining_time":92.05957509,"test":[2.299663651]},
{"learn":[2.061548036],"iteration":480,"passed_time":2213.707776,"remaining_time":87.4437583,"test":[2.299246563]},
{"learn":[2.060892946],"iteration":481,"passed_time":2217.954004,"remaining_time":82.82815782,"test":[2.299104096]},
{"learn":[2.060249452],"iteration":482,"passed_time":2222.269291,"remaining_time":78.21651749,"test":[2.298984421]},
{"learn":[2.059373232],"iteration":483,"passed_time":2226.538462,"remaining_time":73.60457725,"test":[2.298489523]},
{"learn":[2.058589563],"iteration":484,"passed_time":2230.793623,"remaining_time":68.9936172,"test":[2.298165089]},
{"learn":[2.057989829],"iteration":485,"passed_time":2235.012736,"remaining_time":64.38308293,"test":[2.297955452]},
{"learn":[2.057467496],"iteration":486,"passed_time":2239.254084,"remaining_time":59.77474968,"test":[2.297797755]},
{"learn":[2.056831159],"iteration":487,"passed_time":2243.511054,"remaining_time":55.16830462,"test":[2.297564136]},
{"learn":[2.056227778],"iteration":488,"passed_time":2247.737212,"remaining_time":50.56259578,"test":[2.297394428]},
{"learn":[2.055502005],"iteration":489,"passed_time":2252.007766,"remaining_time":45.95934217,"test":[2.29718309]},
{"learn":[2.054891487],"iteration":490,"passed_time":2256.263948,"remaining_time":41.3571803,"test":[2.297009157]},
{"learn":[2.054440868],"iteration":491,"passed_time":2260.402257,"remaining_time":36.75450824,"test":[2.296926484]},
{"learn":[2.053738934],"iteration":492,"passed_time":2264.802002,"remaining_time":32.15743207,"test":[2.296755786]},
{"learn":[2.053155783],"iteration":493,"passed_time":2268.997216,"remaining_time":27.55867064,"test":[2.296685641]},
{"learn":[2.052256787],"iteration":494,"passed_time":2273.310663,"remaining_time":22.96273397,"test":[2.296336034]},
{"learn":[2.051666199],"iteration":495,"passed_time":2277.52893,"remaining_time":18.36716879,"test":[2.296139447]},
{"learn":[2.051080653],"iteration":496,"passed_time":2281.761346,"remaining_time":13.77320732,"test":[2.296019979]},
{"learn":[2.050305716],"iteration":497,"passed_time":2286.115541,"remaining_time":9.181186912,"test":[2.295913067]},
{"learn":[2.049691723],"iteration":498,"passed_time":2290.388299,"remaining_time":4.589956511,"test":[2.295668342]},
{"learn":[2.049117508],"iteration":499,"passed_time":2294.671551,"remaining_time":0,"test":[2.295572637]}
]}